{
    "actions": [
        {
            "注释": "第一次转视角",
            "type": "mouse_move",
            "relative": [
                -370,
                0
            ]
        },
        {
            "注释": "按住shit",
            "type": "key",
            "name": "shiftleft",
            "duration": 4,
            "blocking": false
        },
        {
            "注释": "按住 w",
            "type": "key",
            "name": "w",
            "duration": 4,
            "blocking": false
        },
        {
            "注释": "第一段位移时间",
            "type": "wait",
            "duration": 2.15,
            "blocking": true
        },
        {
            "注释": "第二次转视角",
            "type": "mouse_move",
            "relative": [
                230,
                0
            ]
        },
        {
            "注释": "第二段位移时间",
            "type": "wait",
            "duration": 2.5,
            "blocking": true
        },
        {
            "注释": "按表情键 上下左右对应 up/down/left/right",
            "type": "press",
            "key": "down"
        },
        {
            "type": "wait",
            "duration": 2,
            "blocking": true
        },
        {
            "注释": "移动视角看boss",
            "type": "mouse_move",
            "relative": [
                1800,
                0
            ]
        },
        {
            "注释": "需要反向让视角停住",
            "type": "mouse_move",
            "relative": [
                1,
                0
            ]
        }
    ]
}